xaal/__init__.py
xaal/esphome/__init__.py
xaal/esphome/__main__.py
xaal/esphome/bindings.py
xaal/esphome/gw.py
xaal_esphome-0.2.6.dist-info/METADATA
xaal_esphome-0.2.6.dist-info/WHEEL
xaal_esphome-0.2.6.dist-info/top_level.txt
xaal_esphome-0.2.6.dist-info/RECORD
